pj/__init__.py
pj/_modidx.py
pj/checks.py
pj/cli.py
pj/core.py
pj/setup.py
pj/ship.py
pj/sync.py
pj_sh-0.0.5.dist-info/licenses/LICENSE
pj_sh-0.0.5.dist-info/METADATA
pj_sh-0.0.5.dist-info/WHEEL
pj_sh-0.0.5.dist-info/entry_points.txt
pj_sh-0.0.5.dist-info/top_level.txt
pj_sh-0.0.5.dist-info/RECORD
