Metadata-Version: 2.4
Name: pj_sh
Version: 0.0.5
Summary: project shell > hyperspace velocity
Home-page: https://github.com/kitled/pj
Author: Kit Ledru
Author-email: kit@ledru.dev
Requires-Python: >=3.9
License-File: LICENSE
Dynamic: author
Dynamic: author-email
Dynamic: description
Dynamic: description-content-type
Dynamic: home-page
Dynamic: license-file
Dynamic: requires-python
Dynamic: summary
